tabular_page_maker/__init__.py
tabular_page_maker/make_link_table.py
tabular_page_maker-0.0.1.dist-info/LICENSE
tabular_page_maker-0.0.1.dist-info/WHEEL
tabular_page_maker-0.0.1.dist-info/METADATA
tabular_page_maker-0.0.1.dist-info/RECORD
