Metadata-Version: 2.1
Name: tabular_page_maker
Version: 0.0.1
Summary: Create tabular pages from YAML.
Author-email: "John C. G. Sturdy" <jcg.sturdy@gmail.com>
Classifier: License :: OSI Approved :: GNU General Public License v3 or later (GPLv3+)
Requires-Dist: pyyaml
